{"id":11654,"permalink":"http:\/\/www.sailusfood.com\/2011\/06\/18\/dondakaya-verusenaga-pappu-vepudu-ivy-gourd-peanut-stir-fry\/","title":"Dondakaya Verusenaga Pappu Vepudu ~ Ivy Gourd Peanut Stir Fry","content":"As long as there's lots of peanuts, this Ivy gourd stir fry recipe is a winner. A classic vegetarian dish served on special occasions as part of an elaborate Andhra thali. The key to this recipe is deep frying tindora slices before sauteing them in a tempering of spices, curry leaves and onions and finishing off with a good dose of roasted peanuts. Fried dondakaya has a nice crispy crust and a mildly spiced flavor that is irresistible. \r\n\r\n\r\n\r\n\r\nDondakaya Verusenaga Pappu Vepudu ~ Ivy Gourd Peanut Stir Fry Recipe\r\nPrep: 30 mts\r\nServes: 4 persons\r\nCuisine: Andhra\r\n.\r\n\r\nIngredients:\r\n\r\n\r\n250 gms \/1\/4 kg Dondakayalu\/Tendli\/Ivy Gourds\r\n\r\n1\/4 cup roasted peanuts\r\n\r\n1 tsp mustard seeds\r\n\r\n1 tsp split black gram dal\/minapa pappu\r\n\r\n15-18 curry leaves\r\n\r\n1 large onion, sliced\r\n\r\n1 tsp red chilli powder\r\n\r\n1\/2 tsp saunf powder\r\n\r\npinch of coriander powder\r\n\r\nsalt to taste\r\n\r\n1\/2 tbsp oil\r\n\r\noil for deep frying\r\n\r\n\r\n\r\n1 Wash the Ivy gourds, nip the tip and tail ends. Slice each into 2, length wise and keep aside.\r\n2 Heat enough oil for deep frying in a vessel, once hot, place the dondakaya pieces into the oil and deep fry till lightly golden in color. Drain and keep aside.\r\n3 Heat a tbsp of oil in a cooking vessel, add the mustard seeds and let them splutter. Add urad dal and allow it to turn red. Add curry leaves and fry for a few seconds till the aroma emanates the kitchen. \r\n4 Add the sliced onions and mix. Add turmeric pwd and mix well. Saute on medium heat for 5-6 minutes, keep sauteing so that it doesn\u00e2\u20ac\u2122t burn. \r\n5 Add red chilli pwd, coriander pwd, saunf pwd and salt and mix. Add the deep fried dondakaya pieces and saute. Add the roasted peanuts and mix. Cook on low-medium flame for 6-7 mts without lid. Turn off heat.\r\n6 Serve warm with steamed rice.\r\n\r\n","image":"http:\/\/www.sailusfood.com\/wp-content\/uploads\/2011\/06\/dondakaya-vepudu.jpg","image-small":"https:\/\/storage.googleapis.com\/turtle-sailusfood\/dondakaya-vepudu-150x150.jpg","image-large":"https:\/\/storage.googleapis.com\/turtle-sailusfood\/dondakaya-vepudu-300x300.jpg","style":["easy","quick","modern"],"course":["main"],"special-diet":["eggless","dairy free","vegetarian","vegan","kid friendly","pregnancy"],"cuisine":["andhra"],"cook-time":"20","prep-time":"10","main-ingredient":["dondakaya","peanuts"],"serves":"4","goes-well-with":["rice"],"author":null,"type":"post","categories":["All Recipes","Andhra Recipes","Indian Fry Recipes","Indian Vegan Recipes","Indian Vegetarian Recipes","Recipes Vegetable Dishes"],"tags":["dondakaya","ivy-gourd","peanuts","stir-fry","tendli"]}