{"id":14246,"permalink":"http:\/\/www.sailusfood.com\/2013\/01\/05\/egg-slice-masala-egg-recipes\/","title":"Egg Slice Masala","content":"Egg Slice Masala\r\n\r\n","image":"http:\/\/www.sailusfood.com\/wp-content\/uploads\/2013\/01\/egg-recipes-indian-style.jpg","image-small":"https:\/\/storage.googleapis.com\/turtle-sailusfood\/egg-recipes-indian-style-150x150.jpg","image-large":"https:\/\/storage.googleapis.com\/turtle-sailusfood\/egg-recipes-indian-style-300x300.jpg","style":["easy","quick","modern"],"course":["main-course"],"special-diet":["egg","nut free","kid friendly","pregnancy"],"cuisine":["south indian"],"cook-time":"30","prep-time":"30","main-ingredient":["eggs"],"serves":"5","goes-well-with":["rice"],"author":null,"type":"post","categories":["All Recipes","Indian Curry Recipes","Indian Egg Recipes","South Indian Recipes"],"tags":["egg-curry","egg-recipes","eggs"]}