{"id":17,"permalink":"http:\/\/www.sailusfood.com\/2005\/11\/16\/benefits-of-bitter-gourd-karela\/","title":"What is Bitter gourd - Karela Benefits","content":"Bitter gourd is the least preferred vegetable among many. But the benefits of Karela should be taken advantage of and if cooked in right manner bitter gourd is really tasty. Bittergourd is highly recommended for diabetics.\r\n\r\nBitter gourd\r\n\r\n\r\nBitter gourd contains vitamin A, B1, B2, and C. It also contains minerals like calcium, phosphorous, iron, copper and potassium. From the ayurvedic perspective, bitter gourd is excellent for balancing Kapha. It helps purify blood tissue, enhances digestion, and stimulates the liver.\r\n\r\nYoung immature bitter gourds are the best for cooking.The skin is bright green in color, the flesh inside is white, and the seeds are small and tender. Mature Karela is not advisable and its better to avoid bitter gourd if you are pregnant or nursing.\r\n\r\nTo prepare bitter gourd for cooking, wash thoroughly, lightly peel the skin, then cut into half lengthwise and scrape out the seeds with a spoon and discard. Cut or slice as called for in your recipe, and blanch for 3-4 minutes in boiling water to which a little salt and turmeric has been added. Drain.\r\n\r\nI prepare bitter gourd dishes regularly. Today's bitter gourd recipe is a tangy bitter gourd gravy curry (in Andhra it goes by the name Kakarakaya Pulusu), the recipe of which I will be posting later in the day. ","main-ingredient":["bitter gourd"],"author":null,"type":"post","categories":["All Recipes","Ayurvedic Cooking - Ayurveda Recipes","Recipes Vegetable Dishes"],"tags":["bittergourd","kakarakaya","karela"]}