{"id":4561,"permalink":"http:\/\/www.sailusfood.com\/2009\/11\/08\/sorakaya-payasam-dhoodi-kheer-bottle-gourd-pudding\/","title":"Sorakaya Payasam ~ Doodhi Kheer for 4th blog birthday","content":"Today, Sailu's Kitchen turns four. Feels incredible! A mere 'thank you' isn't enough to express my gratitude for your affection, support and encouragement, dear readers. I appreciate each and every comment, feedback and emails sent by you. Thank you very much!\r\n\r\n\r\n\r\nLet's celebrate with a low-fat dessert. Sorakaya Payasam is prepared with grated bottle gourd that is roasted in ghee, simmered in milk, sweetened with sugar, flavored with cardamom and saffron and garnished with toasted cashew nuts and almonds.\r\n\r\nSorakaya Payasam Recipe\r\nCooking Time: 45 mts\r\nCuisine: Andhra\r\nServes 5-6 persons\r\n. \r\n\r\nIngredients:\r\n\r\n2 1\/4 cups low fat milk\r\n\r\n1 cup grated bottle gourd\/sorakaya\/dhoodi, squeeze out water\r\n\r\n4 tbsps sugar (adjust)\r\n\r\n1\/2 tsp cardamom pwd\r\n\r\npinch of saffron, mix with 1 tsp milk\r\n\r\n5-6 cashew nuts\/almonds, toasted\r\n\r\n1\/2 tbsp ghee\r\n\r\n1 Heat a vessel, add ghee and toast the cashew nuts and almonds till golden brown. Remove from vessel, keep aside.\r\n2 In the same vessel, add the grated bottle gourd and saute for 5-6 mts. Add the boiled milk and simmer for 15-16 mts, stirring once in a while. Add sugar and simmer for another 10-12 mts, stirring once in a while.\r\n3 Add the cardamom pwd, saffron and toasted cashews and almonds. Serve warm or refrigerate until chilled. It tastes good both warm and chilled. \r\n\r\n","image":"http:\/\/www.sailusfood.com\/wp-content\/uploads\/2009\/10\/doodhi-kheer-bottle-gourd-pudding.jpg","image-small":"https:\/\/storage.googleapis.com\/turtle-sailusfood\/doodhi-kheer-bottle-gourd-pudding-150x150.jpg","image-large":"https:\/\/storage.googleapis.com\/turtle-sailusfood\/doodhi-kheer-bottle-gourd-pudding-300x300.jpg","style":["traditional"],"course":["dessert"],"special-diet":["healthy","dairy"],"cuisine":["indian","andhra"],"cook-time":"40","prep-time":"15","main-ingredient":["bottle gourd","milk"],"serves":"4","author":null,"type":"post","categories":["All Recipes","Andhra Recipes","Indian Milk Recipes","Indian Sweets Recipes","Indian Vegetarian Recipes","Misc","Personal","Recipes Vegetable Dishes","Sweet Dessert Recipes"],"tags":["bottle-gourd","kheer","sorakaya"]}