{"id":5,"permalink":"http:\/\/www.sailusfood.com\/2005\/11\/08\/welcome-to-my-blog\/","title":"Welcome To My Indian Food Blog - Sailu's Kitchen!","content":"Welcome to my Indian food &amp; good health blog. I am Sailaja, your host. My food blog is to provide a variety of ideas and recipes for healthy Indian cooking. You will find a lot of Andhra Vantalu (cooking) and recipes in my blog, more of easy vegetarian recipes and a few chicken and meat recipes as well. \r\n\r\nHoping to build a food &amp; home remedies resource blog filled with recipes, cooking tips and ideas related to food from India.\r\n\r\n\r\n\r\nWell, my tryst with Ayurveda is amazing and hope to share some amazing results I had from Ayurvedic cooking. Its so simple and I believe everyone should be aware of the secrets of Ayurveda and herbs. Indian food spices are nutritive with immense medicinal value is immense and I hope to share some of my own tips and herbs I use in my cooking.","image":"http:\/\/www.sailusfood.com\/wp-content\/uploads\/kondapalli_toy1.jpg","image-small":"https:\/\/storage.googleapis.com\/turtle-sailusfood\/kondapalli_toy1-150x150.jpg","image-large":"https:\/\/storage.googleapis.com\/turtle-sailusfood\/kondapalli_toy1-300x300.jpg","author":null,"type":"post","categories":["All Recipes","Misc"],"tags":["andhra-recipes","easy-vegetarian-recipes","indian-food-blog","indian-food-recipes"]}